svut/svut.core
svut/svutCreate.py
svut/svutRun.py
svut/svut_h.sv
svut/template.cpp
svut/template.sv
test/bats/docs/source/conf.py
svut-1.9.3.dist-info/AUTHORS
svut-1.9.3.dist-info/LICENSE
svut-1.9.3.dist-info/METADATA
svut-1.9.3.dist-info/WHEEL
svut-1.9.3.dist-info/top_level.txt
svut-1.9.3.dist-info/RECORD
