Metadata-Version: 2.1
Name: svut
Version: 1.9.3
Summary: SystemVerilog Unit Test (SVUT)
Home-page: https://github.com/dpretet/svut
Author: Damien Pretet
Author-email: Damien Pretet <damien.pretet@me.com>, Sarah Clark <sarahclark@google.com>, Sebastian Schaetz <seb.schaetz@gmail.com>
License: The MIT License
Project-URL: Homepage, https://github.com/dpretet/svut
Project-URL: Bug Tracker, https://github.com/dpretet/svut/issues
Keywords: verilog,systemverilog,testing
Classifier: Programming Language :: Python :: 3
Classifier: License :: OSI Approved :: MIT License
Classifier: Operating System :: OS Independent
Requires-Python: >=3.7, <4
License-File: LICENSE
License-File: AUTHORS
